project_cleaner/__init__.py
project_cleaner/__main__.py
project_cleaner/cleaner.py
project_cleaner-0.1.1.dist-info/licenses/LICENSE
project_cleaner-0.1.1.dist-info/METADATA
project_cleaner-0.1.1.dist-info/WHEEL
project_cleaner-0.1.1.dist-info/entry_points.txt
project_cleaner-0.1.1.dist-info/top_level.txt
project_cleaner-0.1.1.dist-info/RECORD
